nengo_edge/__init__.py
nengo_edge/cli.py
nengo_edge/config.py
nengo_edge/micro_runner.py
nengo_edge/network_runner.py
nengo_edge/py.typed
nengo_edge/ragged.py
nengo_edge/saved_model_runner.py
nengo_edge/tflite_runner.py
nengo_edge/validate.py
nengo_edge/version.py
nengo_edge/device_modules/__init__.py
nengo_edge/device_modules/coral_device.py
nengo_edge/device_modules/np_mfcc.py
nengo_edge/device_modules/tests/__init__.py
nengo_edge/device_modules/tests/test_coral_device.py
nengo_edge/device_modules/tests/test_np_mfcc.py
nengo_edge/tests/__init__.py
nengo_edge/tests/test_cli.py
nengo_edge/tests/test_config.py
nengo_edge/tests/test_micro_runner.py
nengo_edge/tests/test_network_runner.py
nengo_edge/tests/test_ragged.py
nengo_edge/tests/test_saved_model_runner.py
nengo_edge/tests/test_tflite_runner.py
nengo_edge/tests/test_validate.py
nengo_edge/tests/test_version.py
nengo_edge-24.3.6.dist-info/LICENSE.rst
nengo_edge-24.3.6.dist-info/METADATA
nengo_edge-24.3.6.dist-info/WHEEL
nengo_edge-24.3.6.dist-info/entry_points.txt
nengo_edge-24.3.6.dist-info/top_level.txt
nengo_edge-24.3.6.dist-info/RECORD
