Metadata-Version: 2.1
Name: nengo-edge
Version: 24.3.6
Summary: Tools for working with NengoEdge
Home-page: https://github.com/nengo/nengo-edge
Author: Applied Brain Research
Author-email: edge-info@appliedbrainresearch.com
License: MIT license
Classifier: Development Status :: 4 - Beta
Classifier: Framework :: Nengo
Classifier: License :: OSI Approved :: MIT License
Classifier: Operating System :: Microsoft :: Windows
Classifier: Operating System :: POSIX :: Linux
Classifier: Programming Language :: Python
Classifier: Programming Language :: Python :: 3.10
Classifier: Programming Language :: Python :: 3.7
Classifier: Programming Language :: Python :: 3.8
Classifier: Programming Language :: Python :: 3.9
Classifier: Topic :: Scientific/Engineering
Classifier: Topic :: Scientific/Engineering :: Artificial Intelligence
Requires-Python: >=3.8
License-File: LICENSE.rst
Requires-Dist: click >=8.1.3
Requires-Dist: packaging >=20.9
Requires-Dist: pyserial >=3.5
Requires-Dist: rich >=13.3.1
Requires-Dist: soundfile >=0.12.1
Requires-Dist: numpy >=1.23.0
Provides-Extra: all
Requires-Dist: jupyter >=1.0.0 ; extra == 'all'
Requires-Dist: nbsphinx >=0.8.11 ; extra == 'all'
Requires-Dist: nengo-sphinx-theme >=20.9 ; extra == 'all'
Requires-Dist: numpydoc >=1.4.0 ; extra == 'all'
Requires-Dist: sounddevice >=0.4.5 ; extra == 'all'
Requires-Dist: sphinx-click >=5.0.0 ; extra == 'all'
Requires-Dist: sphinx-tabs >=3.2.0 ; extra == 'all'
Requires-Dist: tensorflow >=2.10.0 ; extra == 'all'
Requires-Dist: tensorflow-text >=2.13.0 ; extra == 'all'
Requires-Dist: mypy >=0.901 ; extra == 'all'
Requires-Dist: pytest >=7.1.1 ; extra == 'all'
Requires-Dist: pytest-rng >=1.0.0 ; extra == 'all'
Requires-Dist: types-click >=7.1.0 ; extra == 'all'
Provides-Extra: docs
Requires-Dist: jupyter >=1.0.0 ; extra == 'docs'
Requires-Dist: nbsphinx >=0.8.11 ; extra == 'docs'
Requires-Dist: nengo-sphinx-theme >=20.9 ; extra == 'docs'
Requires-Dist: numpydoc >=1.4.0 ; extra == 'docs'
Requires-Dist: sounddevice >=0.4.5 ; extra == 'docs'
Requires-Dist: sphinx-click >=5.0.0 ; extra == 'docs'
Requires-Dist: sphinx-tabs >=3.2.0 ; extra == 'docs'
Provides-Extra: optional
Requires-Dist: tensorflow >=2.10.0 ; extra == 'optional'
Requires-Dist: tensorflow-text >=2.13.0 ; extra == 'optional'
Provides-Extra: tests
Requires-Dist: mypy >=0.901 ; extra == 'tests'
Requires-Dist: pytest >=7.1.1 ; extra == 'tests'
Requires-Dist: pytest-rng >=1.0.0 ; extra == 'tests'
Requires-Dist: types-click >=7.1.0 ; extra == 'tests'
